LICENSE
MANIFEST.in
README
README.md
setup.py
bristol/__init__.py
bristol/cPSE.py
bristol/data.py
bristol/ensembles.py
bristol/spectral.py
bristol/stats.py
bristol/version.py
bristol.egg-info/PKG-INFO
bristol.egg-info/SOURCES.txt
bristol.egg-info/dependency_links.txt
bristol.egg-info/not-zip-safe
bristol.egg-info/requires.txt
bristol.egg-info/top_level.txt
test/test_approach_se.py
test/test_cPSE_vgg11.py
test/test_eigen_circular.py
test/test_eigen_circular_ensemble.py
test/test_gen_coe.py
test/test_gen_cse.py
test/test_gen_cue.py
test/test_kl_distance_symmetric.py
test/test_n_eigen_circular.py
test/test_n_eigen_circular2.py
test/test_spectral_density.py
test/test_thirumalai_mountain.py
test/test_unit_anti.py
test/test_unit_symplectic.py