Metadata-Version: 2.1
Name: bristol
Version: 0.2.9
Summary: Parallel random matrix tools and random matrix theory deep learning applications. Generate matrices from Circular Unitary Ensemble (CUE), Circular Ortogonal Ensemble (COE) and Circular Symplectic Ensemble (CSE). Additional spectral analysis utilities are also implemented, such as computation of spectral density and spectral ergodicity for complexity of deep learning architectures.
Home-page: https://github.com/msuzen/bristol
Author: M.Suzen
Author-email: suzen@acm.org
License: GPL-3
Platform: UNKNOWN
